pms_ray_cluster/__init__.py
pms_ray_cluster/_const.py
pms_ray_cluster/_dependency.py
pms_ray_cluster/_enum.py
pms_ray_cluster/_ray_cluster.py
pms_ray_cluster/_runtime_env_config.py
pms_ray_cluster/_utils.py
pms_ray_cluster-1.5.3.dist-info/METADATA
pms_ray_cluster-1.5.3.dist-info/WHEEL
pms_ray_cluster-1.5.3.dist-info/RECORD
