Metadata-Version: 2.4
Name: pms-ray-cluster
Version: 1.5.3
Summary: repos for pms ray cluster
Author: HyeongSeok Kim
Author-email: tiryul@gmail.com
Requires-Python: ==3.12.*
Classifier: Programming Language :: Python :: 3
Classifier: Programming Language :: Python :: 3.12
Requires-Dist: asyncmy (>=0.2.10,<0.3.0)
Requires-Dist: asyncpg (>=0.29.0,<0.30.0)
Requires-Dist: boto3 (>=1.34.133,<2.0.0)
Requires-Dist: dependency-injector (>=4.46.0,<5.0.0)
Requires-Dist: ffmpeg-python (>=0.2.0,<0.3.0)
Requires-Dist: fire (>=0.6.0,<0.7.0)
Requires-Dist: influxdb-client (>=1.48.0,<2.0.0)
Requires-Dist: loguru
Requires-Dist: openexr (>=3.3.2,<4.0.0)
Requires-Dist: pillow (>=10.4.0,<11.0.0)
Requires-Dist: pms-model-manager (>=1.3.2,<2.0.0)
Requires-Dist: pms-nvidia-processor (>=2.13.0,<2.14.0)
Requires-Dist: prefect (>=3.2.12,<4.0.0)
Requires-Dist: pydantic (>=2.10.6,<3.0.0)
Requires-Dist: pydantic-settings (>=2.7.1,<3.0.0)
Requires-Dist: pymysql (>=1.1.1,<2.0.0)
Requires-Dist: pytest (>=8.3.5,<9.0.0)
Requires-Dist: python-dotenv
Requires-Dist: ray[serve] (==2.40)
Requires-Dist: redis[async] (>=5.2.1,<6.0.0)
Requires-Dist: scenedetect (>=0.6.6,<0.7.0)
Requires-Dist: sourcedefender (>=15.0.12,<16.0.0)
Requires-Dist: sqlalchemy[asyncio] (>=2.0.40,<3.0.0)
Requires-Dist: streamlit (>=1.43.2,<2.0.0)
Requires-Dist: streamlit-autorefresh (>=1.0.1,<2.0.0)
Requires-Dist: tenacity (>=9.1.2,<10.0.0)
Requires-Dist: typer
Requires-Dist: uvloop
